retdec_config_patch/__init__.py
retdec_config_patch/checks.py
retdec_config_patch/cli.py
retdec_config_patch/config.py
retdec_config_patch/decompiler.py
retdec_config_patch/misc.py
retdec_config_patch/paths.py
retdec_config_patch-0.2.2.dist-info/LICENSE
retdec_config_patch-0.2.2.dist-info/METADATA
retdec_config_patch-0.2.2.dist-info/WHEEL
retdec_config_patch-0.2.2.dist-info/entry_points.txt
retdec_config_patch-0.2.2.dist-info/RECORD
