Metadata-Version: 2.1
Name: retdec-config-patch
Version: 0.2.2
Summary: Patch for the broken `--config` option in `retdec-decompiler`
License: MIT
Keywords: patch,retdec,decompiler
Author: PhotonicGluon
Author-email: 25820201+PhotonicGluon@users.noreply.github.com
Requires-Python: >=3.8,<4.0
Classifier: Development Status :: 4 - Beta
Classifier: Intended Audience :: Developers
Classifier: License :: OSI Approved :: MIT License
Classifier: Programming Language :: Python :: 3
Classifier: Programming Language :: Python :: 3.8
Classifier: Programming Language :: Python :: 3.9
Classifier: Programming Language :: Python :: 3.10
Classifier: Programming Language :: Python :: 3.11
Classifier: Programming Language :: Python :: 3.12
Classifier: Topic :: Security
Classifier: Topic :: Software Development :: Disassemblers
Requires-Dist: click (>=8.1.7,<8.2.0)
Requires-Dist: colorama (>=0.4.6,<0.5.0)
Requires-Dist: filelock (>=3.15.1,<3.16.0)
Project-URL: Issues, https://github.com/PhotonicGluon/RetDec-Config-Patch/issues
Project-URL: Repository, https://github.com/PhotonicGluon/RetDec-Config-Patch
